{
  "@type" : "alfa.rt.model.Record",
  "Doc" : "The Payment Dates of the trade relative to the Calculation Periods.",
  "Name" : {
    "@type" : "alfa.rt.model.UdtVersionedName",
    "FullyQualifiedName" : "FpML5.confirmation.CommodityRelativePaymentDates",
    "UdtType" : "recordType"
  },
  "Includes" : [ ],
  "Source" : {
    "@type" : "alfa.rt.model.Union__ModelBaseNode_Source",
    "Contents" : "/#\n   The Payment Dates of the trade relative to the Calculation Periods.\n #/\nrecord FpML5.confirmation.CommodityRelativePaymentDates {\n  # Specifies whether the payment(s) occur relative to a date such as the end of each Calculation Period or the last Pricing Date in each Calculation Period.\n  payRelativeTo : FpML5.confirmation.CommodityPayRelativeToEnum\n\n  # Specifies whether the payment(s) occur relative to the date of a physical event such as issuance of a bill of lading.\n  payRelativeToEvent : string\n\n  # A pointer style reference to the Calculation Periods defined on another leg.\n  calculationPeriodsReference : FpML5.confirmation.CalculationPeriodsReference\n\n  # A pointer style reference to the Calculation Periods Schedule defined on another leg.\n  calculationPeriodsScheduleReference : FpML5.confirmation.CalculationPeriodsScheduleReference\n\n  # A pointer style reference to single-day-duration Calculation Periods defined on another leg.\n  calculationPeriodsDatesReference : FpML5.confirmation.CalculationPeriodsDatesReference\n\n  # Specifies any offset from the adjusted Calculation Period start date, adjusted Calculation Period end date or Calculation Date applicable to each Payment Date.\n  paymentDaysOffset : FpML5.confirmation.DateOffset\n\n  # A pointer style reference to a set of financial business centers defined elsewhere in the document. This set of business centers is used to determine whether a particular day is a business day or not.\n  businessCentersReference : FpML5.confirmation.BusinessCentersReference\n\n  businessCenters : FpML5.confirmation.BusinessCenters\n\n  id : string?\n\n}"
  },
  "ImmediateDependants" : [ {
    "@type" : "alfa.rt.model.UdtVersionedName",
    "FullyQualifiedName" : "FpML5.confirmation.AveragePriceLeg",
    "UdtType" : "recordType"
  }, {
    "@type" : "alfa.rt.model.UdtVersionedName",
    "FullyQualifiedName" : "FpML5.confirmation.CommodityDigitalExercise",
    "UdtType" : "recordType"
  }, {
    "@type" : "alfa.rt.model.UdtVersionedName",
    "FullyQualifiedName" : "FpML5.confirmation.CommodityExercise",
    "UdtType" : "recordType"
  }, {
    "@type" : "alfa.rt.model.UdtVersionedName",
    "FullyQualifiedName" : "FpML5.confirmation.CommodityExerciseBasket",
    "UdtType" : "recordType"
  }, {
    "@type" : "alfa.rt.model.UdtVersionedName",
    "FullyQualifiedName" : "FpML5.confirmation.CommodityInterestLeg",
    "UdtType" : "recordType"
  }, {
    "@type" : "alfa.rt.model.UdtVersionedName",
    "FullyQualifiedName" : "FpML5.confirmation.CommodityReturnLeg",
    "UdtType" : "recordType"
  }, {
    "@type" : "alfa.rt.model.UdtVersionedName",
    "FullyQualifiedName" : "FpML5.confirmation.CommodityVarianceLeg",
    "UdtType" : "recordType"
  }, {
    "@type" : "alfa.rt.model.UdtVersionedName",
    "FullyQualifiedName" : "FpML5.confirmation.FixedPriceLeg",
    "UdtType" : "recordType"
  }, {
    "@type" : "alfa.rt.model.UdtVersionedName",
    "FullyQualifiedName" : "FpML5.confirmation.FloatingPriceLeg",
    "UdtType" : "recordType"
  }, {
    "@type" : "alfa.rt.model.UdtVersionedName",
    "FullyQualifiedName" : "FpML5.confirmation.NonPeriodicFixedPriceLeg",
    "UdtType" : "recordType"
  }, {
    "@type" : "alfa.rt.model.UdtVersionedName",
    "FullyQualifiedName" : "FpML5.confirmation.WeatherLeg",
    "UdtType" : "recordType"
  } ],
  "AllFields" : {
    "payRelativeTo" : {
      "@type" : "alfa.rt.model.Field",
      "Doc" : "Specifies whether the payment(s) occur relative to a date such as the end of each Calculation Period or the last Pricing Date in each Calculation Period.",
      "Name" : "payRelativeTo",
      "DataType" : {
        "@type" : "alfa.rt.model.UdtDataType",
        "FullyQualifiedName" : "FpML5.confirmation.CommodityPayRelativeToEnum",
        "UdtType" : "enumType"
      },
      "DeclTypeDefDataType" : {
        "@type" : "alfa.rt.model.TypeDefDataType",
        "TypeName" : "FpML5.confirmation.CommodityPayRelativeToEnum",
        "FinalType" : {
          "@type" : "alfa.rt.model.UdtDataType",
          "FullyQualifiedName" : "FpML5.confirmation.CommodityPayRelativeToEnum",
          "UdtType" : "enumType"
        }
      },
      "SrcLocation" : {
        "@type" : "alfa.rt.model.Location",
        "path" : "/Users/sadia/IdeaProjects/smt/utils/alfadocs/test/alfa/fpml/conf/fpml-main-5-9.alfa",
        "line" : 24142
      }
    },
    "payRelativeToEvent" : {
      "@type" : "alfa.rt.model.Field",
      "Doc" : "Specifies whether the payment(s) occur relative to the date of a physical event such as issuance of a bill of lading.",
      "Name" : "payRelativeToEvent",
      "DataType" : {
        "@type" : "alfa.rt.model.ScalarDataType",
        "ScalarType" : "stringType"
      },
      "SrcLocation" : {
        "@type" : "alfa.rt.model.Location",
        "path" : "/Users/sadia/IdeaProjects/smt/utils/alfadocs/test/alfa/fpml/conf/fpml-main-5-9.alfa",
        "line" : 24145
      }
    },
    "calculationPeriodsReference" : {
      "@type" : "alfa.rt.model.Field",
      "Doc" : "A pointer style reference to the Calculation Periods defined on another leg.",
      "Name" : "calculationPeriodsReference",
      "DataType" : {
        "@type" : "alfa.rt.model.UdtDataType",
        "FullyQualifiedName" : "FpML5.confirmation.CalculationPeriodsReference",
        "UdtType" : "recordType"
      },
      "DeclTypeDefDataType" : {
        "@type" : "alfa.rt.model.TypeDefDataType",
        "TypeName" : "FpML5.confirmation.CalculationPeriodsReference",
        "FinalType" : {
          "@type" : "alfa.rt.model.UdtDataType",
          "FullyQualifiedName" : "FpML5.confirmation.CalculationPeriodsReference",
          "UdtType" : "recordType"
        }
      },
      "SrcLocation" : {
        "@type" : "alfa.rt.model.Location",
        "path" : "/Users/sadia/IdeaProjects/smt/utils/alfadocs/test/alfa/fpml/conf/fpml-main-5-9.alfa",
        "line" : 24148
      }
    },
    "calculationPeriodsScheduleReference" : {
      "@type" : "alfa.rt.model.Field",
      "Doc" : "A pointer style reference to the Calculation Periods Schedule defined on another leg.",
      "Name" : "calculationPeriodsScheduleReference",
      "DataType" : {
        "@type" : "alfa.rt.model.UdtDataType",
        "FullyQualifiedName" : "FpML5.confirmation.CalculationPeriodsScheduleReference",
        "UdtType" : "recordType"
      },
      "DeclTypeDefDataType" : {
        "@type" : "alfa.rt.model.TypeDefDataType",
        "TypeName" : "FpML5.confirmation.CalculationPeriodsScheduleReference",
        "FinalType" : {
          "@type" : "alfa.rt.model.UdtDataType",
          "FullyQualifiedName" : "FpML5.confirmation.CalculationPeriodsScheduleReference",
          "UdtType" : "recordType"
        }
      },
      "SrcLocation" : {
        "@type" : "alfa.rt.model.Location",
        "path" : "/Users/sadia/IdeaProjects/smt/utils/alfadocs/test/alfa/fpml/conf/fpml-main-5-9.alfa",
        "line" : 24151
      }
    },
    "calculationPeriodsDatesReference" : {
      "@type" : "alfa.rt.model.Field",
      "Doc" : "A pointer style reference to single-day-duration Calculation Periods defined on another leg.",
      "Name" : "calculationPeriodsDatesReference",
      "DataType" : {
        "@type" : "alfa.rt.model.UdtDataType",
        "FullyQualifiedName" : "FpML5.confirmation.CalculationPeriodsDatesReference",
        "UdtType" : "recordType"
      },
      "DeclTypeDefDataType" : {
        "@type" : "alfa.rt.model.TypeDefDataType",
        "TypeName" : "FpML5.confirmation.CalculationPeriodsDatesReference",
        "FinalType" : {
          "@type" : "alfa.rt.model.UdtDataType",
          "FullyQualifiedName" : "FpML5.confirmation.CalculationPeriodsDatesReference",
          "UdtType" : "recordType"
        }
      },
      "SrcLocation" : {
        "@type" : "alfa.rt.model.Location",
        "path" : "/Users/sadia/IdeaProjects/smt/utils/alfadocs/test/alfa/fpml/conf/fpml-main-5-9.alfa",
        "line" : 24154
      }
    },
    "paymentDaysOffset" : {
      "@type" : "alfa.rt.model.Field",
      "Doc" : "Specifies any offset from the adjusted Calculation Period start date, adjusted Calculation Period end date or Calculation Date applicable to each Payment Date.",
      "Name" : "paymentDaysOffset",
      "DataType" : {
        "@type" : "alfa.rt.model.UdtDataType",
        "FullyQualifiedName" : "FpML5.confirmation.DateOffset",
        "UdtType" : "recordType"
      },
      "DeclTypeDefDataType" : {
        "@type" : "alfa.rt.model.TypeDefDataType",
        "TypeName" : "FpML5.confirmation.DateOffset",
        "FinalType" : {
          "@type" : "alfa.rt.model.UdtDataType",
          "FullyQualifiedName" : "FpML5.confirmation.DateOffset",
          "UdtType" : "recordType"
        }
      },
      "SrcLocation" : {
        "@type" : "alfa.rt.model.Location",
        "path" : "/Users/sadia/IdeaProjects/smt/utils/alfadocs/test/alfa/fpml/conf/fpml-main-5-9.alfa",
        "line" : 24157
      }
    },
    "businessCentersReference" : {
      "@type" : "alfa.rt.model.Field",
      "Doc" : "A pointer style reference to a set of financial business centers defined elsewhere in the document. This set of business centers is used to determine whether a particular day is a business day or not.",
      "Name" : "businessCentersReference",
      "DataType" : {
        "@type" : "alfa.rt.model.UdtDataType",
        "FullyQualifiedName" : "FpML5.confirmation.BusinessCentersReference",
        "UdtType" : "recordType"
      },
      "DeclTypeDefDataType" : {
        "@type" : "alfa.rt.model.TypeDefDataType",
        "TypeName" : "FpML5.confirmation.BusinessCentersReference",
        "FinalType" : {
          "@type" : "alfa.rt.model.UdtDataType",
          "FullyQualifiedName" : "FpML5.confirmation.BusinessCentersReference",
          "UdtType" : "recordType"
        }
      },
      "SrcLocation" : {
        "@type" : "alfa.rt.model.Location",
        "path" : "/Users/sadia/IdeaProjects/smt/utils/alfadocs/test/alfa/fpml/conf/fpml-main-5-9.alfa",
        "line" : 24160
      }
    },
    "businessCenters" : {
      "@type" : "alfa.rt.model.Field",
      "Name" : "businessCenters",
      "DataType" : {
        "@type" : "alfa.rt.model.UdtDataType",
        "FullyQualifiedName" : "FpML5.confirmation.BusinessCenters",
        "UdtType" : "recordType"
      },
      "DeclTypeDefDataType" : {
        "@type" : "alfa.rt.model.TypeDefDataType",
        "TypeName" : "FpML5.confirmation.BusinessCenters",
        "FinalType" : {
          "@type" : "alfa.rt.model.UdtDataType",
          "FullyQualifiedName" : "FpML5.confirmation.BusinessCenters",
          "UdtType" : "recordType"
        }
      },
      "SrcLocation" : {
        "@type" : "alfa.rt.model.Location",
        "path" : "/Users/sadia/IdeaProjects/smt/utils/alfadocs/test/alfa/fpml/conf/fpml-main-5-9.alfa",
        "line" : 24163
      }
    },
    "id" : {
      "@type" : "alfa.rt.model.Field",
      "Name" : "id",
      "DataType" : {
        "@type" : "alfa.rt.model.OptionalDataType",
        "ComponentType" : {
          "@type" : "alfa.rt.model.ScalarDataType",
          "ScalarType" : "stringType"
        }
      },
      "SrcLocation" : {
        "@type" : "alfa.rt.model.Location",
        "path" : "/Users/sadia/IdeaProjects/smt/utils/alfadocs/test/alfa/fpml/conf/fpml-main-5-9.alfa",
        "line" : 24165
      }
    }
  },
  "LocalFieldNames" : [ "payRelativeTo", "payRelativeToEvent", "calculationPeriodsReference", "calculationPeriodsScheduleReference", "calculationPeriodsDatesReference", "paymentDaysOffset", "businessCentersReference", "businessCenters", "id" ],
  "IsSynthetic" : false
}