{
  "@type" : "alfa.rt.model.Record",
  "Doc" : "A type used to describe the scope/contents of a report.",
  "Name" : {
    "@type" : "alfa.rt.model.UdtVersionedName",
    "FullyQualifiedName" : "FpML5.reporting.ReportContents",
    "UdtType" : "recordType"
  },
  "Includes" : [ ],
  "Source" : {
    "@type" : "alfa.rt.model.Union__ModelBaseNode_Source",
    "Contents" : "/#\n   A type used to describe the scope/contents of a report.\n #/\nrecord FpML5.reporting.ReportContents {\n  # The party for which this report was generated.\n  partyReference : FpML5.reporting.PartyReference?\n\n  # The account for which this report was generated.\n  accountReference : FpML5.reporting.AccountReference?\n\n  # Used to categorize trades into user-defined categories, such as house trades vs. customer trades.\n  category : string?\n\n  # A classification of the risk class of the trade. FpML defines a simple asset class categorization using a coding scheme.\n  assetClass : string?\n\n  # A classification of the most important risk class of the trade. FpML defines a simple asset class categorization using a coding scheme.\n  primaryAssetClass : string?\n\n  # A classification of additional risk classes of the trade, if any. FpML defines a simple asset class categorization using a coding scheme.\n  secondaryAssetClass : string?\n\n  # A classification of the type of product. FpML defines a simple product categorization using a coding scheme.\n  productType : string?\n\n  # The desired query portfolio.\n  queryPortfolio : FpML5.reporting.QueryPortfolio?\n\n  # The regulatory reporting regime for which this report contains information\n  reportingRegime : FpML5.reporting.ReportingRegimeIdentifier?\n\n}"
  },
  "ImmediateDependants" : [ {
    "@type" : "alfa.rt.model.UdtVersionedName",
    "FullyQualifiedName" : "FpML5.reporting.AllegedCashflow",
    "UdtType" : "recordType"
  }, {
    "@type" : "alfa.rt.model.UdtVersionedName",
    "FullyQualifiedName" : "FpML5.reporting.AllegedNettedCashflow",
    "UdtType" : "recordType"
  }, {
    "@type" : "alfa.rt.model.UdtVersionedName",
    "FullyQualifiedName" : "FpML5.reporting.AssertedCashflow",
    "UdtType" : "recordType"
  }, {
    "@type" : "alfa.rt.model.UdtVersionedName",
    "FullyQualifiedName" : "FpML5.reporting.AssertedNettedCashflow",
    "UdtType" : "recordType"
  }, {
    "@type" : "alfa.rt.model.UdtVersionedName",
    "FullyQualifiedName" : "FpML5.reporting.EventActivityReport",
    "UdtType" : "recordType"
  }, {
    "@type" : "alfa.rt.model.UdtVersionedName",
    "FullyQualifiedName" : "FpML5.reporting.ExposureReport",
    "UdtType" : "recordType"
  }, {
    "@type" : "alfa.rt.model.UdtVersionedName",
    "FullyQualifiedName" : "FpML5.reporting.NettedTradeCashflowsAsserted",
    "UdtType" : "recordType"
  }, {
    "@type" : "alfa.rt.model.UdtVersionedName",
    "FullyQualifiedName" : "FpML5.reporting.PartyReport",
    "UdtType" : "recordType"
  }, {
    "@type" : "alfa.rt.model.UdtVersionedName",
    "FullyQualifiedName" : "FpML5.reporting.PositionActivityReport",
    "UdtType" : "recordType"
  }, {
    "@type" : "alfa.rt.model.UdtVersionedName",
    "FullyQualifiedName" : "FpML5.reporting.PositionReport",
    "UdtType" : "recordType"
  }, {
    "@type" : "alfa.rt.model.UdtVersionedName",
    "FullyQualifiedName" : "FpML5.reporting.RequestPositionReport",
    "UdtType" : "recordType"
  }, {
    "@type" : "alfa.rt.model.UdtVersionedName",
    "FullyQualifiedName" : "FpML5.reporting.RequestValuationReport",
    "UdtType" : "recordType"
  }, {
    "@type" : "alfa.rt.model.UdtVersionedName",
    "FullyQualifiedName" : "FpML5.reporting.ResetReport",
    "UdtType" : "recordType"
  }, {
    "@type" : "alfa.rt.model.UdtVersionedName",
    "FullyQualifiedName" : "FpML5.reporting.TerminatingEventsReport",
    "UdtType" : "recordType"
  }, {
    "@type" : "alfa.rt.model.UdtVersionedName",
    "FullyQualifiedName" : "FpML5.reporting.TradeCashflowsAsserted",
    "UdtType" : "recordType"
  }, {
    "@type" : "alfa.rt.model.UdtVersionedName",
    "FullyQualifiedName" : "FpML5.reporting.ValuationReport",
    "UdtType" : "recordType"
  }, {
    "@type" : "alfa.rt.model.UdtVersionedName",
    "FullyQualifiedName" : "FpML5.reporting.ValuationReportRetracted",
    "UdtType" : "recordType"
  } ],
  "AllFields" : {
    "partyReference" : {
      "@type" : "alfa.rt.model.Field",
      "Doc" : "The party for which this report was generated.",
      "Name" : "partyReference",
      "DataType" : {
        "@type" : "alfa.rt.model.OptionalDataType",
        "ComponentType" : {
          "@type" : "alfa.rt.model.UdtDataType",
          "FullyQualifiedName" : "FpML5.reporting.PartyReference",
          "UdtType" : "recordType"
        }
      },
      "SrcLocation" : {
        "@type" : "alfa.rt.model.Location",
        "path" : "/Users/sadia/IdeaProjects/smt/utils/alfadocs/test/alfa/fpml/rep/fpml-main-5-9.alfa",
        "line" : 29241
      }
    },
    "accountReference" : {
      "@type" : "alfa.rt.model.Field",
      "Doc" : "The account for which this report was generated.",
      "Name" : "accountReference",
      "DataType" : {
        "@type" : "alfa.rt.model.OptionalDataType",
        "ComponentType" : {
          "@type" : "alfa.rt.model.UdtDataType",
          "FullyQualifiedName" : "FpML5.reporting.AccountReference",
          "UdtType" : "recordType"
        }
      },
      "SrcLocation" : {
        "@type" : "alfa.rt.model.Location",
        "path" : "/Users/sadia/IdeaProjects/smt/utils/alfadocs/test/alfa/fpml/rep/fpml-main-5-9.alfa",
        "line" : 29244
      }
    },
    "category" : {
      "@type" : "alfa.rt.model.Field",
      "Doc" : "Used to categorize trades into user-defined categories, such as house trades vs. customer trades.",
      "Name" : "category",
      "DataType" : {
        "@type" : "alfa.rt.model.OptionalDataType",
        "ComponentType" : {
          "@type" : "alfa.rt.model.ScalarDataType",
          "ScalarType" : "stringType"
        }
      },
      "SrcLocation" : {
        "@type" : "alfa.rt.model.Location",
        "path" : "/Users/sadia/IdeaProjects/smt/utils/alfadocs/test/alfa/fpml/rep/fpml-main-5-9.alfa",
        "line" : 29247
      }
    },
    "assetClass" : {
      "@type" : "alfa.rt.model.Field",
      "Doc" : "A classification of the risk class of the trade. FpML defines a simple asset class categorization using a coding scheme.",
      "Name" : "assetClass",
      "DataType" : {
        "@type" : "alfa.rt.model.OptionalDataType",
        "ComponentType" : {
          "@type" : "alfa.rt.model.ScalarDataType",
          "ScalarType" : "stringType"
        }
      },
      "SrcLocation" : {
        "@type" : "alfa.rt.model.Location",
        "path" : "/Users/sadia/IdeaProjects/smt/utils/alfadocs/test/alfa/fpml/rep/fpml-main-5-9.alfa",
        "line" : 29250
      }
    },
    "primaryAssetClass" : {
      "@type" : "alfa.rt.model.Field",
      "Doc" : "A classification of the most important risk class of the trade. FpML defines a simple asset class categorization using a coding scheme.",
      "Name" : "primaryAssetClass",
      "DataType" : {
        "@type" : "alfa.rt.model.OptionalDataType",
        "ComponentType" : {
          "@type" : "alfa.rt.model.ScalarDataType",
          "ScalarType" : "stringType"
        }
      },
      "SrcLocation" : {
        "@type" : "alfa.rt.model.Location",
        "path" : "/Users/sadia/IdeaProjects/smt/utils/alfadocs/test/alfa/fpml/rep/fpml-main-5-9.alfa",
        "line" : 29253
      }
    },
    "secondaryAssetClass" : {
      "@type" : "alfa.rt.model.Field",
      "Doc" : "A classification of additional risk classes of the trade, if any. FpML defines a simple asset class categorization using a coding scheme.",
      "Name" : "secondaryAssetClass",
      "DataType" : {
        "@type" : "alfa.rt.model.OptionalDataType",
        "ComponentType" : {
          "@type" : "alfa.rt.model.ScalarDataType",
          "ScalarType" : "stringType"
        }
      },
      "SrcLocation" : {
        "@type" : "alfa.rt.model.Location",
        "path" : "/Users/sadia/IdeaProjects/smt/utils/alfadocs/test/alfa/fpml/rep/fpml-main-5-9.alfa",
        "line" : 29256
      }
    },
    "productType" : {
      "@type" : "alfa.rt.model.Field",
      "Doc" : "A classification of the type of product. FpML defines a simple product categorization using a coding scheme.",
      "Name" : "productType",
      "DataType" : {
        "@type" : "alfa.rt.model.OptionalDataType",
        "ComponentType" : {
          "@type" : "alfa.rt.model.ScalarDataType",
          "ScalarType" : "stringType"
        }
      },
      "SrcLocation" : {
        "@type" : "alfa.rt.model.Location",
        "path" : "/Users/sadia/IdeaProjects/smt/utils/alfadocs/test/alfa/fpml/rep/fpml-main-5-9.alfa",
        "line" : 29259
      }
    },
    "queryPortfolio" : {
      "@type" : "alfa.rt.model.Field",
      "Doc" : "The desired query portfolio.",
      "Name" : "queryPortfolio",
      "DataType" : {
        "@type" : "alfa.rt.model.OptionalDataType",
        "ComponentType" : {
          "@type" : "alfa.rt.model.UdtDataType",
          "FullyQualifiedName" : "FpML5.reporting.QueryPortfolio",
          "UdtType" : "recordType"
        }
      },
      "SrcLocation" : {
        "@type" : "alfa.rt.model.Location",
        "path" : "/Users/sadia/IdeaProjects/smt/utils/alfadocs/test/alfa/fpml/rep/fpml-main-5-9.alfa",
        "line" : 29262
      }
    },
    "reportingRegime" : {
      "@type" : "alfa.rt.model.Field",
      "Doc" : "The regulatory reporting regime for which this report contains information",
      "Name" : "reportingRegime",
      "DataType" : {
        "@type" : "alfa.rt.model.OptionalDataType",
        "ComponentType" : {
          "@type" : "alfa.rt.model.UdtDataType",
          "FullyQualifiedName" : "FpML5.reporting.ReportingRegimeIdentifier",
          "UdtType" : "recordType"
        }
      },
      "SrcLocation" : {
        "@type" : "alfa.rt.model.Location",
        "path" : "/Users/sadia/IdeaProjects/smt/utils/alfadocs/test/alfa/fpml/rep/fpml-main-5-9.alfa",
        "line" : 29265
      }
    }
  },
  "LocalFieldNames" : [ "partyReference", "accountReference", "category", "assetClass", "primaryAssetClass", "secondaryAssetClass", "productType", "queryPortfolio", "reportingRegime" ],
  "IsSynthetic" : false
}