{
  "@type" : "alfa.rt.model.Record",
  "Doc" : "The quantity of gas to be delivered.",
  "Name" : {
    "@type" : "alfa.rt.model.UdtVersionedName",
    "FullyQualifiedName" : "FpML5.recordkeeping.GasQuality",
    "UdtType" : "recordType"
  },
  "Includes" : [ ],
  "Source" : {
    "@type" : "alfa.rt.model.Union__ModelBaseNode_Source",
    "Contents" : "/#\n   The quantity of gas to be delivered.\n #/\nrecord FpML5.recordkeeping.GasQuality {\n  gasQualityScheme : string?\n\n}"
  },
  "AllFields" : {
    "gasQualityScheme" : {
      "@type" : "alfa.rt.model.Field",
      "Name" : "gasQualityScheme",
      "DataType" : {
        "@type" : "alfa.rt.model.OptionalDataType",
        "ComponentType" : {
          "@type" : "alfa.rt.model.ScalarDataType",
          "ScalarType" : "stringType"
        }
      },
      "SrcLocation" : {
        "@type" : "alfa.rt.model.Location",
        "path" : "/Users/sadia/IdeaProjects/smt/utils/alfadocs/test/alfa/fpml/rk/fpml-main-5-9.alfa",
        "line" : 2878
      }
    }
  },
  "LocalFieldNames" : [ "gasQualityScheme" ],
  "IsSynthetic" : false
}