{
  "@type" : "alfa.rt.model.Enum",
  "Doc" : "The purpose of this element is to disambiguate whether the buyer of the product effectively buys protection or whether he buys risk (and, hence, sells protection) in the case, such as high yields instruments, where no firm standard appears to exist at the execution level.",
  "Name" : {
    "@type" : "alfa.rt.model.UdtVersionedName",
    "FullyQualifiedName" : "FpML5.pretrade.BuyerConventionEnum",
    "UdtType" : "enumType"
  },
  "Includes" : [ ],
  "Source" : {
    "@type" : "alfa.rt.model.Union__ModelBaseNode_Source",
    "Contents" : "/#\n The purpose of this element is to disambiguate whether the buyer of the product effectively buys protection or whether he buys risk (and, hence, sells protection) in the case, such as high yields instruments, where no firm standard appears to exist at the execution level.\n #/\nenum FpML5.pretrade.BuyerConventionEnum {\n    # the buyer of the product effectively buys protection.\n    Protection \n    # the buyer of the product effectively buys risk (and, hence, sells protection).\n    Risk \n\n}"
  },
  "AllFields" : {
    "Protection" : {
      "@type" : "alfa.rt.model.Field",
      "Doc" : "the buyer of the product effectively buys protection.",
      "Name" : "Protection",
      "DataType" : {
        "@type" : "alfa.rt.model.ScalarDataType",
        "ScalarType" : "voidType"
      },
      "SrcLocation" : {
        "@type" : "alfa.rt.model.Location",
        "path" : "/Users/sadia/IdeaProjects/smt/utils/alfadocs/test/alfa/fpml/pt/fpml-main-5-9.alfa",
        "line" : 6248
      }
    },
    "Risk" : {
      "@type" : "alfa.rt.model.Field",
      "Doc" : "the buyer of the product effectively buys risk (and, hence, sells protection).",
      "Name" : "Risk",
      "DataType" : {
        "@type" : "alfa.rt.model.ScalarDataType",
        "ScalarType" : "voidType"
      },
      "SrcLocation" : {
        "@type" : "alfa.rt.model.Location",
        "path" : "/Users/sadia/IdeaProjects/smt/utils/alfadocs/test/alfa/fpml/pt/fpml-main-5-9.alfa",
        "line" : 6250
      }
    }
  },
  "LocalFieldNames" : [ "Protection", "Risk" ],
  "IsSynthetic" : false
}